compas_rbe/__init__.py
compas_rbe/equilibrium/__init__.py
compas_rbe/equilibrium/helpers.py
compas_rbe/equilibrium/interfaceforces/__init__.py
compas_rbe/equilibrium/interfaceforces/interfaceforces_cvx.py
compas_rbe/equilibrium/interfaceforces/interfaceforces_cvxopt.py
compas_rbe-0.1.2rc0.dist-info/AUTHORS.md
compas_rbe-0.1.2rc0.dist-info/LICENSE
compas_rbe-0.1.2rc0.dist-info/METADATA
compas_rbe-0.1.2rc0.dist-info/WHEEL
compas_rbe-0.1.2rc0.dist-info/entry_points.txt
compas_rbe-0.1.2rc0.dist-info/top_level.txt
compas_rbe-0.1.2rc0.dist-info/RECORD
